{
  "baseline": {
    "Double-DQN": {
      "total_reward_mean": 485.12,
      "completion_rate_mean": 0.991,
      "stores_visited_mean": 2.31,
      "avg_premium_pct_mean": -17.44,
      "avg_pref_score_mean": 3.44,
      "avg_expiry_days_mean": 3.52
    },
    "DQN": {
      "total_reward_mean": 472.93,
      "completion_rate_mean": 0.9866,
      "stores_visited_mean": 2.47,
      "avg_premium_pct_mean": -16.2,
      "avg_pref_score_mean": 3.41,
      "avg_expiry_days_mean": 3.5
    },
    "Q-Learning": {
      "total_reward_mean": 395.0,
      "completion_rate_mean": 0.958,
      "stores_visited_mean": 4.95,
      "avg_premium_pct_mean": -9.4,
      "avg_pref_score_mean": 3.4,
      "avg_expiry_days_mean": 3.47
    },
    "PPO": {
      "total_reward_mean": 217.4,
      "completion_rate_mean": 0.979,
      "stores_visited_mean": 2.94,
      "avg_premium_pct_mean": -5.0,
      "avg_pref_score_mean": 3.03,
      "avg_expiry_days_mean": 3.31
    },
    "Greedy": {
      "total_reward_mean": 301.64,
      "completion_rate_mean": 1.0,
      "stores_visited_mean": 6.0,
      "avg_premium_pct_mean": -6.93,
      "avg_pref_score_mean": 3.45,
      "avg_expiry_days_mean": 3.5
    },
    "TimeAware": {
      "total_reward_mean": 229.38,
      "completion_rate_mean": 0.9998,
      "stores_visited_mean": 5.8,
      "avg_premium_pct_mean": -1.77,
      "avg_pref_score_mean": 4.5,
      "avg_expiry_days_mean": 2.42
    },
    "QualityThr": {
      "total_reward_mean": 148.69,
      "completion_rate_mean": 0.9492,
      "stores_visited_mean": 5.32,
      "avg_premium_pct_mean": -0.48,
      "avg_pref_score_mean": 4.17,
      "avg_expiry_days_mean": 1.51
    }
  },
  "Exp0_PPO_Baseline": {
    "Double-DQN": {
      "total_reward_mean": 504.1088,
      "total_reward_std": 46.068,
      "total_reward_median": 513.4978,
      "completion_rate_mean": 0.9862,
      "completion_rate_std": 0.0264,
      "completion_rate_median": 1.0,
      "avg_premium_pct_mean": -18.4528,
      "avg_premium_pct_std": 1.7111,
      "avg_premium_pct_median": -18.6958,
      "avg_pref_score_mean": 3.2666,
      "avg_pref_score_std": 0.2182,
      "avg_pref_score_median": 3.3,
      "avg_expiry_days_mean": 3.4737,
      "avg_expiry_days_std": 0.4758,
      "avg_expiry_days_median": 3.45,
      "stores_visited_mean": 3.48,
      "stores_visited_std": 0.5828,
      "stores_visited_median": 3.0,
      "time_used_mean": 96.35,
      "time_used_std": 15.221,
      "time_used_median": 105.0,
      "items_bought_mean": 19.725,
      "items_bought_std": 0.5286,
      "items_bought_median": 20.0,
      "missing_items_mean": 0.275,
      "missing_items_std": 0.5286,
      "missing_items_median": 0.0
    },
    "DQN": {
      "total_reward_mean": 527.5853,
      "total_reward_std": 63.9954,
      "total_reward_median": 537.6244,
      "completion_rate_mean": 0.9842,
      "completion_rate_std": 0.0272,
      "completion_rate_median": 1.0,
      "avg_premium_pct_mean": -18.6024,
      "avg_premium_pct_std": 2.3334,
      "avg_premium_pct_median": -18.7946,
      "avg_pref_score_mean": 3.6636,
      "avg_pref_score_std": 0.223,
      "avg_pref_score_median": 3.65,
      "avg_expiry_days_mean": 3.4705,
      "avg_expiry_days_std": 0.5419,
      "avg_expiry_days_median": 3.45,
      "stores_visited_mean": 3.44,
      "stores_visited_std": 0.6053,
      "stores_visited_median": 3.0,
      "time_used_mean": 79.45,
      "time_used_std": 20.2472,
      "time_used_median": 75.0,
      "items_bought_mean": 19.685,
      "items_bought_std": 0.5439,
      "items_bought_median": 20.0,
      "missing_items_mean": 0.315,
      "missing_items_std": 0.5439,
      "missing_items_median": 0.0
    },
    "Q-Learning": {
      "total_reward_mean": 272.0139,
      "total_reward_std": 162.3716,
      "total_reward_median": 320.0683,
      "completion_rate_mean": 0.867,
      "completion_rate_std": 0.1798,
      "completion_rate_median": 1.0,
      "avg_premium_pct_mean": -10.6671,
      "avg_premium_pct_std": 3.3643,
      "avg_premium_pct_median": -10.8342,
      "avg_pref_score_mean": 3.1607,
      "avg_pref_score_std": 0.31,
      "avg_pref_score_median": 3.15,
      "avg_expiry_days_mean": 3.4428,
      "avg_expiry_days_std": 0.5366,
      "avg_expiry_days_median": 3.475,
      "stores_visited_mean": 2.095,
      "stores_visited_std": 0.9413,
      "stores_visited_median": 2.0,
      "time_used_mean": 37.325,
      "time_used_std": 19.4671,
      "time_used_median": 35.0,
      "items_bought_mean": 17.34,
      "items_bought_std": 3.5964,
      "items_bought_median": 20.0,
      "missing_items_mean": 2.66,
      "missing_items_std": 3.5964,
      "missing_items_median": 0.0
    },
    "PPO": {
      "total_reward_mean": 217.4211,
      "total_reward_std": 66.058,
      "total_reward_median": 214.3498,
      "completion_rate_mean": 0.9792,
      "completion_rate_std": 0.0317,
      "completion_rate_median": 1.0,
      "avg_premium_pct_mean": -4.9664,
      "avg_premium_pct_std": 3.0778,
      "avg_premium_pct_median": -4.816,
      "avg_pref_score_mean": 3.0342,
      "avg_pref_score_std": 0.2502,
      "avg_pref_score_median": 3.0,
      "avg_expiry_days_mean": 3.4662,
      "avg_expiry_days_std": 0.5285,
      "avg_expiry_days_median": 3.4618,
      "stores_visited_mean": 2.945,
      "stores_visited_std": 0.228,
      "stores_visited_median": 3.0,
      "time_used_mean": 105.025,
      "time_used_std": 0.3527,
      "time_used_median": 105.0,
      "items_bought_mean": 19.585,
      "items_bought_std": 0.6346,
      "items_bought_median": 20.0,
      "missing_items_mean": 0.415,
      "missing_items_std": 0.6346,
      "missing_items_median": 0.0
    },
    "Greedy": {
      "total_reward_mean": 302.9234,
      "total_reward_std": 55.4816,
      "total_reward_median": 302.6336,
      "completion_rate_mean": 1.0,
      "completion_rate_std": 0.0,
      "completion_rate_median": 1.0,
      "avg_premium_pct_mean": -6.9324,
      "avg_premium_pct_std": 2.7101,
      "avg_premium_pct_median": -6.9612,
      "avg_pref_score_mean": 3.4808,
      "avg_pref_score_std": 0.2373,
      "avg_pref_score_median": 3.5,
      "avg_expiry_days_mean": 3.5045,
      "avg_expiry_days_std": 0.4914,
      "avg_expiry_days_median": 3.5,
      "stores_visited_mean": 6.0,
      "stores_visited_std": 0.0,
      "stores_visited_median": 6.0,
      "time_used_mean": 115.0,
      "time_used_std": 0.0,
      "time_used_median": 115.0,
      "items_bought_mean": 20.0,
      "items_bought_std": 0.0,
      "items_bought_median": 20.0,
      "missing_items_mean": 0.0,
      "missing_items_std": 0.0,
      "missing_items_median": 0.0
    },
    "TimeAware": {
      "total_reward_mean": 258.1623,
      "total_reward_std": 67.5502,
      "total_reward_median": 266.8146,
      "completion_rate_mean": 1.0,
      "completion_rate_std": 0.0,
      "completion_rate_median": 1.0,
      "avg_premium_pct_mean": -2.042,
      "avg_premium_pct_std": 3.3421,
      "avg_premium_pct_median": -2.3823,
      "avg_pref_score_mean": 4.4825,
      "avg_pref_score_std": 0.1418,
      "avg_pref_score_median": 4.5,
      "avg_expiry_days_mean": 4.8063,
      "avg_expiry_days_std": 0.3474,
      "avg_expiry_days_median": 4.85,
      "stores_visited_mean": 5.995,
      "stores_visited_std": 0.0705,
      "stores_visited_median": 6.0,
      "time_used_mean": 115.025,
      "time_used_std": 0.9351,
      "time_used_median": 115.0,
      "items_bought_mean": 20.0,
      "items_bought_std": 0.0,
      "items_bought_median": 20.0,
      "missing_items_mean": 0.0,
      "missing_items_std": 0.0,
      "missing_items_median": 0.0
    },
    "QualityThr": {
      "total_reward_mean": 146.6207,
      "total_reward_std": 86.3599,
      "total_reward_median": 149.2911,
      "completion_rate_mean": 0.944,
      "completion_rate_std": 0.0741,
      "completion_rate_median": 0.95,
      "avg_premium_pct_mean": -0.5185,
      "avg_premium_pct_std": 3.8345,
      "avg_premium_pct_median": -0.7083,
      "avg_pref_score_mean": 4.1783,
      "avg_pref_score_std": 0.1747,
      "avg_pref_score_median": 4.182,
      "avg_expiry_days_mean": 1.5209,
      "avg_expiry_days_std": 0.252,
      "avg_expiry_days_median": 1.5263,
      "stores_visited_mean": 5.27,
      "stores_visited_std": 0.9524,
      "stores_visited_median": 6.0,
      "time_used_mean": 110.975,
      "time_used_std": 5.5834,
      "time_used_median": 115.0,
      "items_bought_mean": 18.88,
      "items_bought_std": 1.4818,
      "items_bought_median": 19.0,
      "missing_items_mean": 1.12,
      "missing_items_std": 1.4818,
      "missing_items_median": 1.0
    }
  },
  "Exp1_180min_Revisit": {
    "Double-DQN": {
      "total_reward_mean": 444.3,
      "completion_rate_mean": 0.98,
      "stores_visited_mean": 2.77,
      "avg_premium_pct_mean": -16.6,
      "avg_pref_score_mean": 3.58,
      "avg_expiry_days_mean": 3.41
    },
    "DQN": {
      "total_reward_mean": 555.1,
      "completion_rate_mean": 0.985,
      "stores_visited_mean": 4.29,
      "avg_premium_pct_mean": -20.4,
      "avg_pref_score_mean": 3.63,
      "avg_expiry_days_mean": 3.48
    },
    "Q-Learning": {
      "total_reward_mean": 292.9,
      "completion_rate_mean": 0.885,
      "stores_visited_mean": 2.24,
      "avg_premium_pct_mean": -11.1,
      "avg_pref_score_mean": 3.21,
      "avg_expiry_days_mean": 3.39
    },
    "PPO": {
      "total_reward_mean": 118.4133,
      "total_reward_std": 76.0165,
      "total_reward_median": 122.05,
      "completion_rate_mean": 0.8785,
      "completion_rate_std": 0.0877,
      "completion_rate_median": 0.9,
      "avg_premium_pct_mean": -4.872,
      "avg_premium_pct_std": 2.9484,
      "avg_premium_pct_median": -4.886,
      "avg_pref_score_mean": 3.0125,
      "avg_pref_score_std": 0.2452,
      "avg_pref_score_median": 3.0,
      "avg_expiry_days_mean": 3.4962,
      "avg_expiry_days_std": 0.5406,
      "avg_expiry_days_median": 3.5132,
      "stores_visited_mean": 2.85,
      "stores_visited_std": 0.3571,
      "stores_visited_median": 3.0,
      "time_used_mean": 180.0,
      "time_used_std": 0.0,
      "time_used_median": 180.0,
      "items_bought_mean": 17.57,
      "items_bought_std": 1.7536,
      "items_bought_median": 18.0,
      "missing_items_mean": 2.43,
      "missing_items_std": 1.7536,
      "missing_items_median": 2.0
    },
    "Greedy": {
      "total_reward_mean": 302.9234,
      "total_reward_std": 55.4816,
      "total_reward_median": 302.6336,
      "completion_rate_mean": 1.0,
      "completion_rate_std": 0.0,
      "completion_rate_median": 1.0,
      "avg_premium_pct_mean": -6.9324,
      "avg_premium_pct_std": 2.7101,
      "avg_premium_pct_median": -6.9612,
      "avg_pref_score_mean": 3.4808,
      "avg_pref_score_std": 0.2373,
      "avg_pref_score_median": 3.5,
      "avg_expiry_days_mean": 3.5045,
      "avg_expiry_days_std": 0.4914,
      "avg_expiry_days_median": 3.5,
      "stores_visited_mean": 6.0,
      "stores_visited_std": 0.0,
      "stores_visited_median": 6.0,
      "time_used_mean": 115.0,
      "time_used_std": 0.0,
      "time_used_median": 115.0,
      "items_bought_mean": 20.0,
      "items_bought_std": 0.0,
      "items_bought_median": 20.0,
      "missing_items_mean": 0.0,
      "missing_items_std": 0.0,
      "missing_items_median": 0.0
    },
    "TimeAware": {
      "total_reward_mean": 256.596,
      "total_reward_std": 68.1584,
      "total_reward_median": 259.2337,
      "completion_rate_mean": 0.9962,
      "completion_rate_std": 0.0141,
      "completion_rate_median": 1.0,
      "avg_premium_pct_mean": -1.9934,
      "avg_premium_pct_std": 3.4162,
      "avg_premium_pct_median": -2.0823,
      "avg_pref_score_mean": 4.5275,
      "avg_pref_score_std": 0.1147,
      "avg_pref_score_median": 4.55,
      "avg_expiry_days_mean": 4.9058,
      "avg_expiry_days_std": 0.3264,
      "avg_expiry_days_median": 4.9,
      "stores_visited_mean": 5.96,
      "stores_visited_std": 0.196,
      "stores_visited_median": 6.0,
      "time_used_mean": 116.475,
      "time_used_std": 8.0746,
      "time_used_median": 115.0,
      "items_bought_mean": 19.925,
      "items_bought_std": 0.2817,
      "items_bought_median": 20.0,
      "missing_items_mean": 0.075,
      "missing_items_std": 0.2817,
      "missing_items_median": 0.0
    },
    "QualityThr": {
      "total_reward_mean": 136.3763,
      "total_reward_std": 92.5461,
      "total_reward_median": 141.7039,
      "completion_rate_mean": 0.946,
      "completion_rate_std": 0.0747,
      "completion_rate_median": 0.95,
      "avg_premium_pct_mean": -0.5418,
      "avg_premium_pct_std": 3.8546,
      "avg_premium_pct_median": -0.7706,
      "avg_pref_score_mean": 4.1782,
      "avg_pref_score_std": 0.1748,
      "avg_pref_score_median": 4.182,
      "avg_expiry_days_mean": 1.5206,
      "avg_expiry_days_std": 0.2518,
      "avg_expiry_days_median": 1.5263,
      "stores_visited_mean": 5.285,
      "stores_visited_std": 0.9559,
      "stores_visited_median": 6.0,
      "time_used_mean": 140.925,
      "time_used_std": 24.6022,
      "time_used_median": 165.0,
      "items_bought_mean": 18.92,
      "items_bought_std": 1.4945,
      "items_bought_median": 19.0,
      "missing_items_mean": 1.08,
      "missing_items_std": 1.4945,
      "missing_items_median": 1.0
    }
  },
  "Exp2_10Goods_Store": {
    "Double-DQN": {
      "total_reward_mean": 360.0194,
      "total_reward_std": 95.5715,
      "total_reward_median": 378.9791,
      "completion_rate_mean": 0.8682,
      "completion_rate_std": 0.0721,
      "completion_rate_median": 0.9,
      "avg_premium_pct_mean": -16.6468,
      "avg_premium_pct_std": 2.9411,
      "avg_premium_pct_median": -17.0081,
      "avg_pref_score_mean": 3.1269,
      "avg_pref_score_std": 0.2744,
      "avg_pref_score_median": 3.1292,
      "avg_expiry_days_mean": 3.5139,
      "avg_expiry_days_std": 0.5466,
      "avg_expiry_days_median": 3.5279,
      "stores_visited_mean": 3.615,
      "stores_visited_std": 0.6832,
      "stores_visited_median": 4.0,
      "time_used_mean": 95.975,
      "time_used_std": 14.6944,
      "time_used_median": 105.0,
      "items_bought_mean": 17.365,
      "items_bought_std": 1.4428,
      "items_bought_median": 18.0,
      "missing_items_mean": 2.635,
      "missing_items_std": 1.4428,
      "missing_items_median": 2.0
    },
    "DQN": {
      "total_reward_mean": 313.8239,
      "total_reward_std": 84.7665,
      "total_reward_median": 312.2367,
      "completion_rate_mean": 0.847,
      "completion_rate_std": 0.0653,
      "completion_rate_median": 0.85,
      "avg_premium_pct_mean": -15.1275,
      "avg_premium_pct_std": 2.5452,
      "avg_premium_pct_median": -15.3634,
      "avg_pref_score_mean": 3.1725,
      "avg_pref_score_std": 0.285,
      "avg_pref_score_median": 3.1667,
      "avg_expiry_days_mean": 3.4473,
      "avg_expiry_days_std": 0.5616,
      "avg_expiry_days_median": 3.405,
      "stores_visited_mean": 3.33,
      "stores_visited_std": 0.5207,
      "stores_visited_median": 3.0,
      "time_used_mean": 97.525,
      "time_used_std": 15.6205,
      "time_used_median": 105.0,
      "items_bought_mean": 16.94,
      "items_bought_std": 1.3063,
      "items_bought_median": 17.0,
      "missing_items_mean": 3.06,
      "missing_items_std": 1.3063,
      "missing_items_median": 3.0
    },
    "Q-Learning": {
      "total_reward_mean": 294.4246,
      "total_reward_std": 169.2307,
      "total_reward_median": 342.4787,
      "completion_rate_mean": 0.8795,
      "completion_rate_std": 0.1891,
      "completion_rate_median": 1.0,
      "avg_premium_pct_mean": -11.6951,
      "avg_premium_pct_std": 3.7063,
      "avg_premium_pct_median": -11.7256,
      "avg_pref_score_mean": 3.13,
      "avg_pref_score_std": 0.315,
      "avg_pref_score_median": 3.1519,
      "avg_expiry_days_mean": 3.519,
      "avg_expiry_days_std": 0.5062,
      "avg_expiry_days_median": 3.5477,
      "stores_visited_mean": 3.79,
      "stores_visited_std": 0.9979,
      "stores_visited_median": 4.0,
      "time_used_mean": 73.275,
      "time_used_std": 21.3635,
      "time_used_median": 75.0,
      "items_bought_mean": 17.59,
      "items_bought_std": 3.7818,
      "items_bought_median": 20.0,
      "missing_items_mean": 2.41,
      "missing_items_std": 3.7818,
      "missing_items_median": 0.0
    },
    "PPO": {
      "total_reward_mean": -101.687,
      "total_reward_std": 66.6792,
      "total_reward_median": -100.0153,
      "completion_rate_mean": 0.6343,
      "completion_rate_std": 0.0984,
      "completion_rate_median": 0.65,
      "avg_premium_pct_mean": 1.5117,
      "avg_premium_pct_std": 4.086,
      "avg_premium_pct_median": 1.6904,
      "avg_pref_score_mean": 2.8545,
      "avg_pref_score_std": 0.3051,
      "avg_pref_score_median": 2.8462,
      "avg_expiry_days_mean": 3.4398,
      "avg_expiry_days_std": 0.6802,
      "avg_expiry_days_median": 3.4142,
      "stores_visited_mean": 2.075,
      "stores_visited_std": 0.2634,
      "stores_visited_median": 2.0,
      "time_used_mean": 105.0,
      "time_used_std": 0.0,
      "time_used_median": 105.0,
      "items_bought_mean": 12.685,
      "items_bought_std": 1.9687,
      "items_bought_median": 13.0,
      "missing_items_mean": 7.315,
      "missing_items_std": 1.9687,
      "missing_items_median": 7.0
    },
    "Greedy": {
      "total_reward_mean": 317.9268,
      "total_reward_std": 66.6434,
      "total_reward_median": 317.6524,
      "completion_rate_mean": 0.9997,
      "completion_rate_std": 0.0035,
      "completion_rate_median": 1.0,
      "avg_premium_pct_mean": -7.8633,
      "avg_premium_pct_std": 3.3495,
      "avg_premium_pct_median": -7.8401,
      "avg_pref_score_mean": 3.4064,
      "avg_pref_score_std": 0.2198,
      "avg_pref_score_median": 3.4,
      "avg_expiry_days_mean": 3.4612,
      "avg_expiry_days_std": 0.5064,
      "avg_expiry_days_median": 3.475,
      "stores_visited_mean": 6.0,
      "stores_visited_std": 0.0,
      "stores_visited_median": 6.0,
      "time_used_mean": 115.0,
      "time_used_std": 0.0,
      "time_used_median": 115.0,
      "items_bought_mean": 19.995,
      "items_bought_std": 0.0705,
      "items_bought_median": 20.0,
      "missing_items_mean": 0.005,
      "missing_items_std": 0.0705,
      "missing_items_median": 0.0
    },
    "TimeAware": {
      "total_reward_mean": 177.9797,
      "total_reward_std": 92.9501,
      "total_reward_median": 190.5821,
      "completion_rate_mean": 0.9367,
      "completion_rate_std": 0.1242,
      "completion_rate_median": 1.0,
      "avg_premium_pct_mean": -0.7449,
      "avg_premium_pct_std": 3.0559,
      "avg_premium_pct_median": -0.9658,
      "avg_pref_score_mean": 4.2043,
      "avg_pref_score_std": 0.2013,
      "avg_pref_score_median": 4.2,
      "avg_expiry_days_mean": 4.5222,
      "avg_expiry_days_std": 0.4402,
      "avg_expiry_days_median": 4.5374,
      "stores_visited_mean": 5.465,
      "stores_visited_std": 0.948,
      "stores_visited_median": 6.0,
      "time_used_mean": 107.275,
      "time_used_std": 19.0775,
      "time_used_median": 115.0,
      "items_bought_mean": 18.735,
      "items_bought_std": 2.4849,
      "items_bought_median": 20.0,
      "missing_items_mean": 1.265,
      "missing_items_std": 2.4849,
      "missing_items_median": 0.0
    },
    "QualityThr": {
      "total_reward_mean": 22.6459,
      "total_reward_std": 97.2821,
      "total_reward_median": 13.3938,
      "completion_rate_mean": 0.7625,
      "completion_rate_std": 0.1227,
      "completion_rate_median": 0.8,
      "avg_premium_pct_mean": 0.244,
      "avg_premium_pct_std": 4.0147,
      "avg_premium_pct_median": 0.4081,
      "avg_pref_score_mean": 4.1035,
      "avg_pref_score_std": 0.1992,
      "avg_pref_score_median": 4.1026,
      "avg_expiry_days_mean": 1.4776,
      "avg_expiry_days_std": 0.286,
      "avg_expiry_days_median": 1.4721,
      "stores_visited_mean": 4.695,
      "stores_visited_std": 0.8955,
      "stores_visited_median": 5.0,
      "time_used_mean": 107.375,
      "time_used_std": 5.0234,
      "time_used_median": 105.0,
      "items_bought_mean": 15.25,
      "items_bought_std": 2.4531,
      "items_bought_median": 16.0,
      "missing_items_mean": 4.75,
      "missing_items_std": 2.4531,
      "missing_items_median": 4.0
    }
  },
  "Exp3_80pct_Avail": {
    "Double-DQN": {
      "total_reward_mean": 523.7835,
      "total_reward_std": 42.3462,
      "total_reward_median": 522.9967,
      "completion_rate_mean": 0.99,
      "completion_rate_std": 0.02,
      "completion_rate_median": 1.0,
      "avg_premium_pct_mean": -18.3941,
      "avg_premium_pct_std": 1.824,
      "avg_premium_pct_median": -18.4771,
      "avg_pref_score_mean": 3.6451,
      "avg_pref_score_std": 0.1767,
      "avg_pref_score_median": 3.6671,
      "avg_expiry_days_mean": 3.4949,
      "avg_expiry_days_std": 0.5108,
      "avg_expiry_days_median": 3.5,
      "stores_visited_mean": 2.815,
      "stores_visited_std": 0.6639,
      "stores_visited_median": 3.0,
      "time_used_mean": 80.4,
      "time_used_std": 23.1806,
      "time_used_median": 75.0,
      "items_bought_mean": 19.8,
      "items_bought_std": 0.4,
      "items_bought_median": 20.0,
      "missing_items_mean": 0.2,
      "missing_items_std": 0.4,
      "missing_items_median": 0.0
    },
    "DQN": {
      "total_reward_mean": 567.2883,
      "total_reward_std": 39.0116,
      "total_reward_median": 570.2014,
      "completion_rate_mean": 0.9947,
      "completion_rate_std": 0.0153,
      "completion_rate_median": 1.0,
      "avg_premium_pct_mean": -20.8219,
      "avg_premium_pct_std": 1.5823,
      "avg_premium_pct_median": -20.9153,
      "avg_pref_score_mean": 3.3514,
      "avg_pref_score_std": 0.1773,
      "avg_pref_score_median": 3.35,
      "avg_expiry_days_mean": 3.5087,
      "avg_expiry_days_std": 0.5291,
      "avg_expiry_days_median": 3.5,
      "stores_visited_mean": 3.355,
      "stores_visited_std": 0.5648,
      "stores_visited_median": 3.0,
      "time_used_mean": 83.125,
      "time_used_std": 19.2901,
      "time_used_median": 80.0,
      "items_bought_mean": 19.895,
      "items_bought_std": 0.3066,
      "items_bought_median": 20.0,
      "missing_items_mean": 0.105,
      "missing_items_std": 0.3066,
      "missing_items_median": 0.0
    },
    "Q-Learning": {
      "total_reward_mean": 475.2857,
      "total_reward_std": 68.43,
      "total_reward_median": 488.6275,
      "completion_rate_mean": 0.9905,
      "completion_rate_std": 0.0478,
      "completion_rate_median": 1.0,
      "avg_premium_pct_mean": -15.9742,
      "avg_premium_pct_std": 2.3014,
      "avg_premium_pct_median": -16.3348,
      "avg_pref_score_mean": 3.2981,
      "avg_pref_score_std": 0.1823,
      "avg_pref_score_median": 3.3,
      "avg_expiry_days_mean": 3.5631,
      "avg_expiry_days_std": 0.4897,
      "avg_expiry_days_median": 3.55,
      "stores_visited_mean": 2.94,
      "stores_visited_std": 0.6375,
      "stores_visited_median": 3.0,
      "time_used_mean": 53.875,
      "time_used_std": 12.7714,
      "time_used_median": 55.0,
      "items_bought_mean": 19.81,
      "items_bought_std": 0.956,
      "items_bought_median": 20.0,
      "missing_items_mean": 0.19,
      "missing_items_std": 0.956,
      "missing_items_median": 0.0
    },
    "PPO": {
      "total_reward_mean": 276.6583,
      "total_reward_std": 56.8217,
      "total_reward_median": 280.6747,
      "completion_rate_mean": 0.9993,
      "completion_rate_std": 0.0061,
      "completion_rate_median": 1.0,
      "avg_premium_pct_mean": -7.396,
      "avg_premium_pct_std": 2.6807,
      "avg_premium_pct_median": -7.6271,
      "avg_pref_score_mean": 2.9614,
      "avg_pref_score_std": 0.1919,
      "avg_pref_score_median": 3.0,
      "avg_expiry_days_mean": 3.4904,
      "avg_expiry_days_std": 0.5125,
      "avg_expiry_days_median": 3.45,
      "stores_visited_mean": 2.985,
      "stores_visited_std": 0.1216,
      "stores_visited_median": 3.0,
      "time_used_mean": 105.0,
      "time_used_std": 0.0,
      "time_used_median": 105.0,
      "items_bought_mean": 19.985,
      "items_bought_std": 0.1216,
      "items_bought_median": 20.0,
      "missing_items_mean": 0.015,
      "missing_items_std": 0.1216,
      "missing_items_median": 0.0
    },
    "Greedy": {
      "total_reward_mean": 366.3804,
      "total_reward_std": 38.5496,
      "total_reward_median": 367.0709,
      "completion_rate_mean": 1.0,
      "completion_rate_std": 0.0,
      "completion_rate_median": 1.0,
      "avg_premium_pct_mean": -9.7328,
      "avg_premium_pct_std": 1.9465,
      "avg_premium_pct_median": -9.7691,
      "avg_pref_score_mean": 3.654,
      "avg_pref_score_std": 0.1799,
      "avg_pref_score_median": 3.65,
      "avg_expiry_days_mean": 3.5565,
      "avg_expiry_days_std": 0.4657,
      "avg_expiry_days_median": 3.55,
      "stores_visited_mean": 6.0,
      "stores_visited_std": 0.0,
      "stores_visited_median": 6.0,
      "time_used_mean": 115.0,
      "time_used_std": 0.0,
      "time_used_median": 115.0,
      "items_bought_mean": 20.0,
      "items_bought_std": 0.0,
      "items_bought_median": 20.0,
      "missing_items_mean": 0.0,
      "missing_items_std": 0.0,
      "missing_items_median": 0.0
    },
    "TimeAware": {
      "total_reward_mean": 261.7451,
      "total_reward_std": 63.6057,
      "total_reward_median": 263.7541,
      "completion_rate_mean": 1.0,
      "completion_rate_std": 0.0,
      "completion_rate_median": 1.0,
      "avg_premium_pct_mean": -1.995,
      "avg_premium_pct_std": 3.1658,
      "avg_premium_pct_median": -2.2135,
      "avg_pref_score_mean": 4.5678,
      "avg_pref_score_std": 0.1049,
      "avg_pref_score_median": 4.55,
      "avg_expiry_days_mean": 4.9135,
      "avg_expiry_days_std": 0.3226,
      "avg_expiry_days_median": 4.9,
      "stores_visited_mean": 6.0,
      "stores_visited_std": 0.0,
      "stores_visited_median": 6.0,
      "time_used_mean": 115.0,
      "time_used_std": 0.0,
      "time_used_median": 115.0,
      "items_bought_mean": 20.0,
      "items_bought_std": 0.0,
      "items_bought_median": 20.0,
      "missing_items_mean": 0.0,
      "missing_items_std": 0.0,
      "missing_items_median": 0.0
    },
    "QualityThr": {
      "total_reward_mean": 167.7548,
      "total_reward_std": 70.7499,
      "total_reward_median": 173.0442,
      "completion_rate_mean": 0.9853,
      "completion_rate_std": 0.0406,
      "completion_rate_median": 1.0,
      "avg_premium_pct_mean": -0.2416,
      "avg_premium_pct_std": 3.3396,
      "avg_premium_pct_median": -0.4278,
      "avg_pref_score_mean": 4.1941,
      "avg_pref_score_std": 0.1665,
      "avg_pref_score_median": 4.2,
      "avg_expiry_days_mean": 1.5192,
      "avg_expiry_days_std": 0.2539,
      "avg_expiry_days_median": 1.5,
      "stores_visited_mean": 5.71,
      "stores_visited_std": 0.7252,
      "stores_visited_median": 6.0,
      "time_used_mean": 113.6,
      "time_used_std": 4.0669,
      "time_used_median": 115.0,
      "items_bought_mean": 19.705,
      "items_bought_std": 0.8112,
      "items_bought_median": 20.0,
      "missing_items_mean": 0.295,
      "missing_items_std": 0.8112,
      "missing_items_median": 0.0
    }
  }
}